oraczenhq/__init__.py
oraczenhq/fastapi_middlware/__init__.py
oraczenhq/fastapi_middlware/main.py
oraczenhq_authzen_fastapi_middleware-1.0.1.dist-info/METADATA
oraczenhq_authzen_fastapi_middleware-1.0.1.dist-info/WHEEL
oraczenhq_authzen_fastapi_middleware-1.0.1.dist-info/top_level.txt
oraczenhq_authzen_fastapi_middleware-1.0.1.dist-info/RECORD
