Metadata-Version: 2.4
Name: oraczenhq-authzen-fastapi-middleware
Version: 1.0.1
Summary: AuthZen FastAPI Middleware
Requires-Dist: httpx<1.0.0,>=0.28.1
Requires-Dist: cryptography<46.0.0,>=45.0.3
Requires-Dist: fastapi<1.0.0,>=0.115.0
Requires-Dist: python-jose<4.0.0,>=3.5.0
Requires-Dist: pydantic<3.0.0,>=2.11.0
Dynamic: description-content-type
Dynamic: requires-dist
Dynamic: summary
